{
  "run": [
    {
      "filePath": "/webapp/index.html",
      "previewMode": 1,
      "dataMode": 1,
      "workspace": "withoutWorkspace",
      "ui5ActiveVersion": null,
      "ui5VerSource": null,
      "isDefaultVersion": 0,
      "urlParameters": [],
      "hashParameter": "",
      "backendSystem": [],
      "_metadata": {
        "id": 5321360,
        "runnerId": "webapprunner",
        "displayName": "Run index.html",
        "lastRunTimeStamp": 1515193686137
      }
    },
    {
      "filePath": "/webapp/local_index.html",
      "previewMode": 1,
      "dataMode": 1,
      "workspace": "withoutWorkspace",
      "ui5ActiveVersion": null,
      "ui5VerSource": null,
      "isDefaultVersion": 0,
      "urlParameters": [],
      "hashParameter": "",
      "backendSystem": [],
      "_metadata": {
        "id": 3335991,
        "runnerId": "webapprunner",
        "displayName": "Run local_index.html",
        "lastRunTimeStamp": 1515171189208
      }
    },
    {
      "filePath": "/webapp/index.html",
      "previewMode": 1,
      "dataMode": 1,
      "workspace": "withoutWorkspace",
      "ui5ActiveVersion": null,
      "ui5VerSource": null,
      "isDefaultVersion": 0,
      "urlParameters": [],
      "hashParameter": "",
      "backendSystem": [],
      "_metadata": {
        "id": 5813120,
        "runnerId": "webapprunner",
        "displayName": "Run index.html 1",
        "lastRunTimeStamp": 1513895892320
      }
    },
    {
      "filePath": "/webapp/test/flpSandboxMockServer.html",
      "previewMode": 1,
      "dataMode": 1,
      "workspace": "withoutWorkspace",
      "ui5ActiveVersion": null,
      "ui5VerSource": null,
      "isDefaultVersion": 0,
      "urlParameters": [],
      "hashParameter": "",
      "backendSystem": [],
      "_metadata": {
        "id": 2029986,
        "runnerId": "webapprunner",
        "displayName": "Run flpSandbox.html",
        "lastRunTimeStamp": 1513869829819
      }
    },
    {
      "filePath": "/WebContent/test/flpSandboxMockServer.html",
      "previewMode": 1,
      "dataMode": 1,
      "workspace": "withoutWorkspace",
      "ui5ActiveVersion": null,
      "ui5VerSource": null,
      "isDefaultVersion": 0,
      "urlParameters": [
        {
          "paramName": "",
          "paramValue": ""
        }
      ],
      "hashParameter": "",
      "backendSystem": [],
      "_metadata": {
        "id": 2511785,
        "runnerId": "webapprunner",
        "displayName": "Run flpSandboxMockServer.html",
        "lastRunTimeStamp": 1513868568488
      }
    },
    {
      "filePath": "/webapp/Component.js",
      "previewMode": 1,
      "dataMode": 1,
      "workspace": "withoutWorkspace",
      "ui5ActiveVersion": null,
      "ui5VerSource": null,
      "isDefaultVersion": 0,
      "urlParameters": [
        {
          "paramName": "",
          "paramValue": ""
        },
        {
          "paramName": "",
          "paramValue": ""
        }
      ],
      "hashParameter": "",
      "backendSystem": [],
      "_metadata": {
        "id": 3610802,
        "runnerId": "fiorirunner",
        "displayName": "Run Component.js",
        "lastRunTimeStamp": 1513868442969
      }
    }
  ]
}